Metadata-Version: 2.1
Name: jk-simpleusermgr
Version: 0.2020.4.16
Summary: This python module implements a very simple user manager. Such a simple user manager is convenient in a variety of situations for small applications.
Home-page: https://github.com/jkpubsrc/python-module-jk-simpleusermgr
Author: Jürgen Knauth
Author-email: pubsrc@binary-overflow.de
License: Apache 2.0
Download-URL: https://github.com/jkpubsrc/python-module-jk-simpleusermgr/tarball/0.2020.4.16
Keywords: user
Platform: UNKNOWN
Classifier: Development Status :: 3 - Alpha
Classifier: License :: OSI Approved :: Apache Software License
